[{"name":"pip_services3_rabbitmq","qualifiedName":"pip_services3_rabbitmq","href":"pip_services3_rabbitmq/pip_services3_rabbitmq-library.html","type":"library","overriddenDepth":0},{"name":"DefaultRabbitMQFactory","qualifiedName":"pip_services3_rabbitmq.DefaultRabbitMQFactory","href":"pip_services3_rabbitmq/DefaultRabbitMQFactory-class.html","type":"class","overriddenDepth":0,"enclosedBy":{"name":"pip_services3_rabbitmq","type":"library"}},{"name":"operator ==","qualifiedName":"pip_services3_rabbitmq.DefaultRabbitMQFactory.==","href":"pip_services3_rabbitmq/DefaultRabbitMQFactory/operator_equals.html","type":"method","overriddenDepth":0,"enclosedBy":{"name":"DefaultRabbitMQFactory","type":"class"}},{"name":"DefaultRabbitMQFactory","qualifiedName":"pip_services3_rabbitmq.DefaultRabbitMQFactory.DefaultRabbitMQFactory","href":"pip_services3_rabbitmq/DefaultRabbitMQFactory/DefaultRabbitMQFactory.html","type":"constructor","overriddenDepth":0,"enclosedBy":{"name":"DefaultRabbitMQFactory","type":"class"}},{"name":"Descriptor3","qualifiedName":"pip_services3_rabbitmq.DefaultRabbitMQFactory.Descriptor3","href":"pip_services3_rabbitmq/DefaultRabbitMQFactory/Descriptor3.html","type":"property","overriddenDepth":0,"enclosedBy":{"name":"DefaultRabbitMQFactory","type":"class"}},{"name":"RabbitMQMessageQueue3Descriptor","qualifiedName":"pip_services3_rabbitmq.DefaultRabbitMQFactory.RabbitMQMessageQueue3Descriptor","href":"pip_services3_rabbitmq/DefaultRabbitMQFactory/RabbitMQMessageQueue3Descriptor.html","type":"property","overriddenDepth":0,"enclosedBy":{"name":"DefaultRabbitMQFactory","type":"class"}},{"name":"RabbitMQMessageQueueDescriptor","qualifiedName":"pip_services3_rabbitmq.DefaultRabbitMQFactory.RabbitMQMessageQueueDescriptor","href":"pip_services3_rabbitmq/DefaultRabbitMQFactory/RabbitMQMessageQueueDescriptor.html","type":"property","overriddenDepth":0,"enclosedBy":{"name":"DefaultRabbitMQFactory","type":"class"}},{"name":"RabbitMQMessageQueueFactory3Descriptor","qualifiedName":"pip_services3_rabbitmq.DefaultRabbitMQFactory.RabbitMQMessageQueueFactory3Descriptor","href":"pip_services3_rabbitmq/DefaultRabbitMQFactory/RabbitMQMessageQueueFactory3Descriptor.html","type":"property","overriddenDepth":0,"enclosedBy":{"name":"DefaultRabbitMQFactory","type":"class"}},{"name":"RabbitMQMessageQueueFactoryDescriptor","qualifiedName":"pip_services3_rabbitmq.DefaultRabbitMQFactory.RabbitMQMessageQueueFactoryDescriptor","href":"pip_services3_rabbitmq/DefaultRabbitMQFactory/RabbitMQMessageQueueFactoryDescriptor.html","type":"property","overriddenDepth":0,"enclosedBy":{"name":"DefaultRabbitMQFactory","type":"class"}},{"name":"canCreate","qualifiedName":"pip_services3_rabbitmq.DefaultRabbitMQFactory.canCreate","href":"pip_services3_rabbitmq/DefaultRabbitMQFactory/canCreate.html","type":"method","overriddenDepth":1,"enclosedBy":{"name":"DefaultRabbitMQFactory","type":"class"}},{"name":"create","qualifiedName":"pip_services3_rabbitmq.DefaultRabbitMQFactory.create","href":"pip_services3_rabbitmq/DefaultRabbitMQFactory/create.html","type":"method","overriddenDepth":1,"enclosedBy":{"name":"DefaultRabbitMQFactory","type":"class"}},{"name":"descriptor","qualifiedName":"pip_services3_rabbitmq.DefaultRabbitMQFactory.descriptor","href":"pip_services3_rabbitmq/DefaultRabbitMQFactory/descriptor.html","type":"property","overriddenDepth":0,"enclosedBy":{"name":"DefaultRabbitMQFactory","type":"class"}},{"name":"hashCode","qualifiedName":"pip_services3_rabbitmq.DefaultRabbitMQFactory.hashCode","href":"pip_services3_rabbitmq/DefaultRabbitMQFactory/hashCode.html","type":"property","overriddenDepth":0,"enclosedBy":{"name":"DefaultRabbitMQFactory","type":"class"}},{"name":"noSuchMethod","qualifiedName":"pip_services3_rabbitmq.DefaultRabbitMQFactory.noSuchMethod","href":"pip_services3_rabbitmq/DefaultRabbitMQFactory/noSuchMethod.html","type":"method","overriddenDepth":0,"enclosedBy":{"name":"DefaultRabbitMQFactory","type":"class"}},{"name":"register","qualifiedName":"pip_services3_rabbitmq.DefaultRabbitMQFactory.register","href":"pip_services3_rabbitmq/DefaultRabbitMQFactory/register.html","type":"method","overriddenDepth":0,"enclosedBy":{"name":"DefaultRabbitMQFactory","type":"class"}},{"name":"registerAsType","qualifiedName":"pip_services3_rabbitmq.DefaultRabbitMQFactory.registerAsType","href":"pip_services3_rabbitmq/DefaultRabbitMQFactory/registerAsType.html","type":"method","overriddenDepth":0,"enclosedBy":{"name":"DefaultRabbitMQFactory","type":"class"}},{"name":"runtimeType","qualifiedName":"pip_services3_rabbitmq.DefaultRabbitMQFactory.runtimeType","href":"pip_services3_rabbitmq/DefaultRabbitMQFactory/runtimeType.html","type":"property","overriddenDepth":0,"enclosedBy":{"name":"DefaultRabbitMQFactory","type":"class"}},{"name":"toString","qualifiedName":"pip_services3_rabbitmq.DefaultRabbitMQFactory.toString","href":"pip_services3_rabbitmq/DefaultRabbitMQFactory/toString.html","type":"method","overriddenDepth":0,"enclosedBy":{"name":"DefaultRabbitMQFactory","type":"class"}},{"name":"RabbitMQConnectionResolver","qualifiedName":"pip_services3_rabbitmq.RabbitMQConnectionResolver","href":"pip_services3_rabbitmq/RabbitMQConnectionResolver-class.html","type":"class","overriddenDepth":0,"enclosedBy":{"name":"pip_services3_rabbitmq","type":"library"}},{"name":"operator ==","qualifiedName":"pip_services3_rabbitmq.RabbitMQConnectionResolver.==","href":"pip_services3_rabbitmq/RabbitMQConnectionResolver/operator_equals.html","type":"method","overriddenDepth":0,"enclosedBy":{"name":"RabbitMQConnectionResolver","type":"class"}},{"name":"RabbitMQConnectionResolver","qualifiedName":"pip_services3_rabbitmq.RabbitMQConnectionResolver.RabbitMQConnectionResolver","href":"pip_services3_rabbitmq/RabbitMQConnectionResolver/RabbitMQConnectionResolver.html","type":"constructor","overriddenDepth":0,"enclosedBy":{"name":"RabbitMQConnectionResolver","type":"class"}},{"name":"compose","qualifiedName":"pip_services3_rabbitmq.RabbitMQConnectionResolver.compose","href":"pip_services3_rabbitmq/RabbitMQConnectionResolver/compose.html","type":"method","overriddenDepth":0,"enclosedBy":{"name":"RabbitMQConnectionResolver","type":"class"}},{"name":"configure","qualifiedName":"pip_services3_rabbitmq.RabbitMQConnectionResolver.configure","href":"pip_services3_rabbitmq/RabbitMQConnectionResolver/configure.html","type":"method","overriddenDepth":1,"enclosedBy":{"name":"RabbitMQConnectionResolver","type":"class"}},{"name":"connectionResolver","qualifiedName":"pip_services3_rabbitmq.RabbitMQConnectionResolver.connectionResolver","href":"pip_services3_rabbitmq/RabbitMQConnectionResolver/connectionResolver.html","type":"property","overriddenDepth":0,"enclosedBy":{"name":"RabbitMQConnectionResolver","type":"class"}},{"name":"credentialResolver","qualifiedName":"pip_services3_rabbitmq.RabbitMQConnectionResolver.credentialResolver","href":"pip_services3_rabbitmq/RabbitMQConnectionResolver/credentialResolver.html","type":"property","overriddenDepth":0,"enclosedBy":{"name":"RabbitMQConnectionResolver","type":"class"}},{"name":"hashCode","qualifiedName":"pip_services3_rabbitmq.RabbitMQConnectionResolver.hashCode","href":"pip_services3_rabbitmq/RabbitMQConnectionResolver/hashCode.html","type":"property","overriddenDepth":0,"enclosedBy":{"name":"RabbitMQConnectionResolver","type":"class"}},{"name":"noSuchMethod","qualifiedName":"pip_services3_rabbitmq.RabbitMQConnectionResolver.noSuchMethod","href":"pip_services3_rabbitmq/RabbitMQConnectionResolver/noSuchMethod.html","type":"method","overriddenDepth":0,"enclosedBy":{"name":"RabbitMQConnectionResolver","type":"class"}},{"name":"resolve","qualifiedName":"pip_services3_rabbitmq.RabbitMQConnectionResolver.resolve","href":"pip_services3_rabbitmq/RabbitMQConnectionResolver/resolve.html","type":"method","overriddenDepth":0,"enclosedBy":{"name":"RabbitMQConnectionResolver","type":"class"}},{"name":"runtimeType","qualifiedName":"pip_services3_rabbitmq.RabbitMQConnectionResolver.runtimeType","href":"pip_services3_rabbitmq/RabbitMQConnectionResolver/runtimeType.html","type":"property","overriddenDepth":0,"enclosedBy":{"name":"RabbitMQConnectionResolver","type":"class"}},{"name":"setReferences","qualifiedName":"pip_services3_rabbitmq.RabbitMQConnectionResolver.setReferences","href":"pip_services3_rabbitmq/RabbitMQConnectionResolver/setReferences.html","type":"method","overriddenDepth":1,"enclosedBy":{"name":"RabbitMQConnectionResolver","type":"class"}},{"name":"toString","qualifiedName":"pip_services3_rabbitmq.RabbitMQConnectionResolver.toString","href":"pip_services3_rabbitmq/RabbitMQConnectionResolver/toString.html","type":"method","overriddenDepth":0,"enclosedBy":{"name":"RabbitMQConnectionResolver","type":"class"}},{"name":"RabbitMQMessageQueue","qualifiedName":"pip_services3_rabbitmq.RabbitMQMessageQueue","href":"pip_services3_rabbitmq/RabbitMQMessageQueue-class.html","type":"class","overriddenDepth":0,"enclosedBy":{"name":"pip_services3_rabbitmq","type":"library"}},{"name":"operator ==","qualifiedName":"pip_services3_rabbitmq.RabbitMQMessageQueue.==","href":"pip_services3_rabbitmq/RabbitMQMessageQueue/operator_equals.html","type":"method","overriddenDepth":0,"enclosedBy":{"name":"RabbitMQMessageQueue","type":"class"}},{"name":"RabbitMQMessageQueue","qualifiedName":"pip_services3_rabbitmq.RabbitMQMessageQueue.RabbitMQMessageQueue","href":"pip_services3_rabbitmq/RabbitMQMessageQueue/RabbitMQMessageQueue.html","type":"constructor","overriddenDepth":0,"enclosedBy":{"name":"RabbitMQMessageQueue","type":"class"}},{"name":"abandon","qualifiedName":"pip_services3_rabbitmq.RabbitMQMessageQueue.abandon","href":"pip_services3_rabbitmq/RabbitMQMessageQueue/abandon.html","type":"method","overriddenDepth":2,"enclosedBy":{"name":"RabbitMQMessageQueue","type":"class"}},{"name":"beginListen","qualifiedName":"pip_services3_rabbitmq.RabbitMQMessageQueue.beginListen","href":"pip_services3_rabbitmq/RabbitMQMessageQueue/beginListen.html","type":"method","overriddenDepth":1,"enclosedBy":{"name":"RabbitMQMessageQueue","type":"class"}},{"name":"capabilities","qualifiedName":"pip_services3_rabbitmq.RabbitMQMessageQueue.capabilities","href":"pip_services3_rabbitmq/RabbitMQMessageQueue/capabilities.html","type":"property","overriddenDepth":0,"enclosedBy":{"name":"RabbitMQMessageQueue","type":"class"}},{"name":"clear","qualifiedName":"pip_services3_rabbitmq.RabbitMQMessageQueue.clear","href":"pip_services3_rabbitmq/RabbitMQMessageQueue/clear.html","type":"method","overriddenDepth":1,"enclosedBy":{"name":"RabbitMQMessageQueue","type":"class"}},{"name":"close","qualifiedName":"pip_services3_rabbitmq.RabbitMQMessageQueue.close","href":"pip_services3_rabbitmq/RabbitMQMessageQueue/close.html","type":"method","overriddenDepth":2,"enclosedBy":{"name":"RabbitMQMessageQueue","type":"class"}},{"name":"complete","qualifiedName":"pip_services3_rabbitmq.RabbitMQMessageQueue.complete","href":"pip_services3_rabbitmq/RabbitMQMessageQueue/complete.html","type":"method","overriddenDepth":2,"enclosedBy":{"name":"RabbitMQMessageQueue","type":"class"}},{"name":"configure","qualifiedName":"pip_services3_rabbitmq.RabbitMQMessageQueue.configure","href":"pip_services3_rabbitmq/RabbitMQMessageQueue/configure.html","type":"method","overriddenDepth":2,"enclosedBy":{"name":"RabbitMQMessageQueue","type":"class"}},{"name":"connectionResolver","qualifiedName":"pip_services3_rabbitmq.RabbitMQMessageQueue.connectionResolver","href":"pip_services3_rabbitmq/RabbitMQMessageQueue/connectionResolver.html","type":"property","overriddenDepth":0,"enclosedBy":{"name":"RabbitMQMessageQueue","type":"class"}},{"name":"counters","qualifiedName":"pip_services3_rabbitmq.RabbitMQMessageQueue.counters","href":"pip_services3_rabbitmq/RabbitMQMessageQueue/counters.html","type":"property","overriddenDepth":0,"enclosedBy":{"name":"RabbitMQMessageQueue","type":"class"}},{"name":"credentialResolver","qualifiedName":"pip_services3_rabbitmq.RabbitMQMessageQueue.credentialResolver","href":"pip_services3_rabbitmq/RabbitMQMessageQueue/credentialResolver.html","type":"property","overriddenDepth":0,"enclosedBy":{"name":"RabbitMQMessageQueue","type":"class"}},{"name":"endListen","qualifiedName":"pip_services3_rabbitmq.RabbitMQMessageQueue.endListen","href":"pip_services3_rabbitmq/RabbitMQMessageQueue/endListen.html","type":"method","overriddenDepth":2,"enclosedBy":{"name":"RabbitMQMessageQueue","type":"class"}},{"name":"getCapabilities","qualifiedName":"pip_services3_rabbitmq.RabbitMQMessageQueue.getCapabilities","href":"pip_services3_rabbitmq/RabbitMQMessageQueue/getCapabilities.html","type":"method","overriddenDepth":1,"enclosedBy":{"name":"RabbitMQMessageQueue","type":"class"}},{"name":"getName","qualifiedName":"pip_services3_rabbitmq.RabbitMQMessageQueue.getName","href":"pip_services3_rabbitmq/RabbitMQMessageQueue/getName.html","type":"method","overriddenDepth":1,"enclosedBy":{"name":"RabbitMQMessageQueue","type":"class"}},{"name":"hashCode","qualifiedName":"pip_services3_rabbitmq.RabbitMQMessageQueue.hashCode","href":"pip_services3_rabbitmq/RabbitMQMessageQueue/hashCode.html","type":"property","overriddenDepth":0,"enclosedBy":{"name":"RabbitMQMessageQueue","type":"class"}},{"name":"interval","qualifiedName":"pip_services3_rabbitmq.RabbitMQMessageQueue.interval","href":"pip_services3_rabbitmq/RabbitMQMessageQueue/interval.html","type":"property","overriddenDepth":0,"enclosedBy":{"name":"RabbitMQMessageQueue","type":"class"}},{"name":"isOpen","qualifiedName":"pip_services3_rabbitmq.RabbitMQMessageQueue.isOpen","href":"pip_services3_rabbitmq/RabbitMQMessageQueue/isOpen.html","type":"method","overriddenDepth":2,"enclosedBy":{"name":"RabbitMQMessageQueue","type":"class"}},{"name":"listen","qualifiedName":"pip_services3_rabbitmq.RabbitMQMessageQueue.listen","href":"pip_services3_rabbitmq/RabbitMQMessageQueue/listen.html","type":"method","overriddenDepth":2,"enclosedBy":{"name":"RabbitMQMessageQueue","type":"class"}},{"name":"logger","qualifiedName":"pip_services3_rabbitmq.RabbitMQMessageQueue.logger","href":"pip_services3_rabbitmq/RabbitMQMessageQueue/logger.html","type":"property","overriddenDepth":0,"enclosedBy":{"name":"RabbitMQMessageQueue","type":"class"}},{"name":"moveToDeadLetter","qualifiedName":"pip_services3_rabbitmq.RabbitMQMessageQueue.moveToDeadLetter","href":"pip_services3_rabbitmq/RabbitMQMessageQueue/moveToDeadLetter.html","type":"method","overriddenDepth":2,"enclosedBy":{"name":"RabbitMQMessageQueue","type":"class"}},{"name":"name","qualifiedName":"pip_services3_rabbitmq.RabbitMQMessageQueue.name","href":"pip_services3_rabbitmq/RabbitMQMessageQueue/name.html","type":"property","overriddenDepth":0,"enclosedBy":{"name":"RabbitMQMessageQueue","type":"class"}},{"name":"noSuchMethod","qualifiedName":"pip_services3_rabbitmq.RabbitMQMessageQueue.noSuchMethod","href":"pip_services3_rabbitmq/RabbitMQMessageQueue/noSuchMethod.html","type":"method","overriddenDepth":0,"enclosedBy":{"name":"RabbitMQMessageQueue","type":"class"}},{"name":"open","qualifiedName":"pip_services3_rabbitmq.RabbitMQMessageQueue.open","href":"pip_services3_rabbitmq/RabbitMQMessageQueue/open.html","type":"method","overriddenDepth":1,"enclosedBy":{"name":"RabbitMQMessageQueue","type":"class"}},{"name":"openWithParams","qualifiedName":"pip_services3_rabbitmq.RabbitMQMessageQueue.openWithParams","href":"pip_services3_rabbitmq/RabbitMQMessageQueue/openWithParams.html","type":"method","overriddenDepth":1,"enclosedBy":{"name":"RabbitMQMessageQueue","type":"class"}},{"name":"peek","qualifiedName":"pip_services3_rabbitmq.RabbitMQMessageQueue.peek","href":"pip_services3_rabbitmq/RabbitMQMessageQueue/peek.html","type":"method","overriddenDepth":2,"enclosedBy":{"name":"RabbitMQMessageQueue","type":"class"}},{"name":"peekBatch","qualifiedName":"pip_services3_rabbitmq.RabbitMQMessageQueue.peekBatch","href":"pip_services3_rabbitmq/RabbitMQMessageQueue/peekBatch.html","type":"method","overriddenDepth":2,"enclosedBy":{"name":"RabbitMQMessageQueue","type":"class"}},{"name":"readMessageCount","qualifiedName":"pip_services3_rabbitmq.RabbitMQMessageQueue.readMessageCount","href":"pip_services3_rabbitmq/RabbitMQMessageQueue/readMessageCount.html","type":"method","overriddenDepth":2,"enclosedBy":{"name":"RabbitMQMessageQueue","type":"class"}},{"name":"receive","qualifiedName":"pip_services3_rabbitmq.RabbitMQMessageQueue.receive","href":"pip_services3_rabbitmq/RabbitMQMessageQueue/receive.html","type":"method","overriddenDepth":2,"enclosedBy":{"name":"RabbitMQMessageQueue","type":"class"}},{"name":"renewLock","qualifiedName":"pip_services3_rabbitmq.RabbitMQMessageQueue.renewLock","href":"pip_services3_rabbitmq/RabbitMQMessageQueue/renewLock.html","type":"method","overriddenDepth":2,"enclosedBy":{"name":"RabbitMQMessageQueue","type":"class"}},{"name":"runtimeType","qualifiedName":"pip_services3_rabbitmq.RabbitMQMessageQueue.runtimeType","href":"pip_services3_rabbitmq/RabbitMQMessageQueue/runtimeType.html","type":"property","overriddenDepth":0,"enclosedBy":{"name":"RabbitMQMessageQueue","type":"class"}},{"name":"send","qualifiedName":"pip_services3_rabbitmq.RabbitMQMessageQueue.send","href":"pip_services3_rabbitmq/RabbitMQMessageQueue/send.html","type":"method","overriddenDepth":2,"enclosedBy":{"name":"RabbitMQMessageQueue","type":"class"}},{"name":"sendAsObject","qualifiedName":"pip_services3_rabbitmq.RabbitMQMessageQueue.sendAsObject","href":"pip_services3_rabbitmq/RabbitMQMessageQueue/sendAsObject.html","type":"method","overriddenDepth":1,"enclosedBy":{"name":"RabbitMQMessageQueue","type":"class"}},{"name":"setReferences","qualifiedName":"pip_services3_rabbitmq.RabbitMQMessageQueue.setReferences","href":"pip_services3_rabbitmq/RabbitMQMessageQueue/setReferences.html","type":"method","overriddenDepth":1,"enclosedBy":{"name":"RabbitMQMessageQueue","type":"class"}},{"name":"toString","qualifiedName":"pip_services3_rabbitmq.RabbitMQMessageQueue.toString","href":"pip_services3_rabbitmq/RabbitMQMessageQueue/toString.html","type":"method","overriddenDepth":1,"enclosedBy":{"name":"RabbitMQMessageQueue","type":"class"}},{"name":"RabbitMQMessageQueueFactory","qualifiedName":"pip_services3_rabbitmq.RabbitMQMessageQueueFactory","href":"pip_services3_rabbitmq/RabbitMQMessageQueueFactory-class.html","type":"class","overriddenDepth":0,"enclosedBy":{"name":"pip_services3_rabbitmq","type":"library"}},{"name":"operator ==","qualifiedName":"pip_services3_rabbitmq.RabbitMQMessageQueueFactory.==","href":"pip_services3_rabbitmq/RabbitMQMessageQueueFactory/operator_equals.html","type":"method","overriddenDepth":0,"enclosedBy":{"name":"RabbitMQMessageQueueFactory","type":"class"}},{"name":"MemoryQueueDescriptor","qualifiedName":"pip_services3_rabbitmq.RabbitMQMessageQueueFactory.MemoryQueueDescriptor","href":"pip_services3_rabbitmq/RabbitMQMessageQueueFactory/MemoryQueueDescriptor.html","type":"property","overriddenDepth":0,"enclosedBy":{"name":"RabbitMQMessageQueueFactory","type":"class"}},{"name":"RabbitMQMessageQueueFactory","qualifiedName":"pip_services3_rabbitmq.RabbitMQMessageQueueFactory.RabbitMQMessageQueueFactory","href":"pip_services3_rabbitmq/RabbitMQMessageQueueFactory/RabbitMQMessageQueueFactory.html","type":"constructor","overriddenDepth":0,"enclosedBy":{"name":"RabbitMQMessageQueueFactory","type":"class"}},{"name":"canCreate","qualifiedName":"pip_services3_rabbitmq.RabbitMQMessageQueueFactory.canCreate","href":"pip_services3_rabbitmq/RabbitMQMessageQueueFactory/canCreate.html","type":"method","overriddenDepth":1,"enclosedBy":{"name":"RabbitMQMessageQueueFactory","type":"class"}},{"name":"config","qualifiedName":"pip_services3_rabbitmq.RabbitMQMessageQueueFactory.config","href":"pip_services3_rabbitmq/RabbitMQMessageQueueFactory/config.html","type":"property","overriddenDepth":0,"enclosedBy":{"name":"RabbitMQMessageQueueFactory","type":"class"}},{"name":"configure","qualifiedName":"pip_services3_rabbitmq.RabbitMQMessageQueueFactory.configure","href":"pip_services3_rabbitmq/RabbitMQMessageQueueFactory/configure.html","type":"method","overriddenDepth":0,"enclosedBy":{"name":"RabbitMQMessageQueueFactory","type":"class"}},{"name":"create","qualifiedName":"pip_services3_rabbitmq.RabbitMQMessageQueueFactory.create","href":"pip_services3_rabbitmq/RabbitMQMessageQueueFactory/create.html","type":"method","overriddenDepth":1,"enclosedBy":{"name":"RabbitMQMessageQueueFactory","type":"class"}},{"name":"descriptor","qualifiedName":"pip_services3_rabbitmq.RabbitMQMessageQueueFactory.descriptor","href":"pip_services3_rabbitmq/RabbitMQMessageQueueFactory/descriptor.html","type":"property","overriddenDepth":0,"enclosedBy":{"name":"RabbitMQMessageQueueFactory","type":"class"}},{"name":"hashCode","qualifiedName":"pip_services3_rabbitmq.RabbitMQMessageQueueFactory.hashCode","href":"pip_services3_rabbitmq/RabbitMQMessageQueueFactory/hashCode.html","type":"property","overriddenDepth":0,"enclosedBy":{"name":"RabbitMQMessageQueueFactory","type":"class"}},{"name":"noSuchMethod","qualifiedName":"pip_services3_rabbitmq.RabbitMQMessageQueueFactory.noSuchMethod","href":"pip_services3_rabbitmq/RabbitMQMessageQueueFactory/noSuchMethod.html","type":"method","overriddenDepth":0,"enclosedBy":{"name":"RabbitMQMessageQueueFactory","type":"class"}},{"name":"register","qualifiedName":"pip_services3_rabbitmq.RabbitMQMessageQueueFactory.register","href":"pip_services3_rabbitmq/RabbitMQMessageQueueFactory/register.html","type":"method","overriddenDepth":0,"enclosedBy":{"name":"RabbitMQMessageQueueFactory","type":"class"}},{"name":"registerAsType","qualifiedName":"pip_services3_rabbitmq.RabbitMQMessageQueueFactory.registerAsType","href":"pip_services3_rabbitmq/RabbitMQMessageQueueFactory/registerAsType.html","type":"method","overriddenDepth":0,"enclosedBy":{"name":"RabbitMQMessageQueueFactory","type":"class"}},{"name":"runtimeType","qualifiedName":"pip_services3_rabbitmq.RabbitMQMessageQueueFactory.runtimeType","href":"pip_services3_rabbitmq/RabbitMQMessageQueueFactory/runtimeType.html","type":"property","overriddenDepth":0,"enclosedBy":{"name":"RabbitMQMessageQueueFactory","type":"class"}},{"name":"toString","qualifiedName":"pip_services3_rabbitmq.RabbitMQMessageQueueFactory.toString","href":"pip_services3_rabbitmq/RabbitMQMessageQueueFactory/toString.html","type":"method","overriddenDepth":0,"enclosedBy":{"name":"RabbitMQMessageQueueFactory","type":"class"}}]
